<?xml version="1.0" encoding="UTF-8" standalone="no"?><mesh><config><name>MeshIneBits Batch 16</name><date>Fri Jan 13 12:48:24 CET 2023</date><dimension-bit><height>8.0</height><width>24.0</width><length>160.0</length></dimension-bit><part-skirt><height>633.75</height><radius>324.6200741927641</radius></part-skirt></config><batch><batch-number>16</batch-number><number-of-bits>72</number-of-bits><layer><layer-height>346.5</layer-height><move-working-space><return/><go-to><x>2507.0947890921575</x></go-to></move-working-space><bit><id-bit>1152</id-bit><no-cutting/><sub-bit><id>1153</id><plate>115</plate><slot>3</slot><grip-center><x>288.64552776294124</x><y>61.09469332915832</y></grip-center><rotation>-37.85990806284623</rotation><pos-in-layer><x>81.55073867078363</x><y>1121.0946933291584</y></pos-in-layer><point><id>0</id><x>-16.83235826641254</x><y>-7.590232334524018</y></point><point><id>1</id><x>-76.83235826641254</x><y>1.4097676654759823</y></point><ref-line-rot>-8.530765609948096</ref-line-rot></sub-bit></bit><move-working-space/><bit><id-bit>1153</id-bit><no-cutting/><sub-bit><id>1154</id><plate>115</plate><slot>4</slot><grip-center><x>293.81054569082596</x><y>-45.934357570872834</y></grip-center><rotation>-37.85990806284623</rotation><pos-in-layer><x>86.71575659866858</x><y>1014.0656424291271</y></pos-in-layer><point><id>0</id><x>52.26327526125942</x><y>9.499870357440955</y></point><point><id>1</id><x>76.26327526125942</x><y>-8.500129642559045</y></point><ref-line-rot>-36.86989764584401</ref-line-rot></sub-bit></bit><move-working-space/><bit><id-bit>1154</id-bit><no-cutting/><sub-bit><id>1155</id><plate>115</plate><slot>5</slot><grip-center><x>297.0133054424707</x><y>22.474813757140524</y></grip-center><rotation>-37.85990806284623</rotation><pos-in-layer><x>89.91851635031298</x><y>1082.4748137571405</y></pos-in-layer><point><id>0</id><x>13.42032603298793</x><y>9.499874586956281</y></point><point><id>1</id><x>76.42032603298793</x><y>-8.500125413043719</y></point><ref-line-rot>-15.945395900922858</ref-line-rot></sub-bit></bit><move-working-space/><bit><id-bit>1155</id-bit><no-cutting/><sub-bit><id>1156</id><plate>115</plate><slot>6</slot><grip-center><x>297.4509162587274</x><y>-13.288791776497995</y></grip-center><rotation>-37.85990806284623</rotation><pos-in-layer><x>90.35612716656988</x><y>1046.7112082235021</y></pos-in-layer><point><id>0</id><x>26.799294420334945</x><y>9.499872472198547</y></point><point><id>1</id><x>74.79929442033495</x><y>-8.500127527801453</y></point><ref-line-rot>-20.55604521958346</ref-line-rot></sub-bit></bit></layer><layer><layer-height>354.75</layer-height><move-working-space><go-to><x>1918.022127656895</x></go-to></move-working-space><bit><id-bit>1156</id-bit><no-cutting/><sub-bit><id>1157</id><plate>115</plate><slot>7</slot><grip-center><x>-315.30943407396035</x><y>2.256196909348837</y></grip-center><rotation>-37.69005707308495</rotation><pos-in-layer><x>66.66843826914464</x><y>1062.256196909349</y></pos-in-layer><point><id>0</id><x>-76.50001667687525</x><y>9.499919720562758</y></point><point><id>1</id><x>-62.50001667687525</x><y>-8.500080279437242</y></point><ref-line-rot>-52.125016348901795</ref-line-rot></sub-bit></bit><move-working-space/><bit><id-bit>1157</id-bit><no-cutting/><sub-bit><id>1158</id><plate>115</plate><slot>8</slot><grip-center><x>-310.07445215511046</x><y>-33.57356143297133</y></grip-center><rotation>-37.69005707308495</rotation><pos-in-layer><x>71.90342018799447</x><y>1026.4264385670285</y></pos-in-layer><point><id>0</id><x>-76.50000615518115</x><y>2.499916260895162</y></point><point><id>1</id><x>-58.500006155181154</x><y>-8.500083739104838</y></point><ref-line-rot>-31.42956561483852</ref-line-rot></sub-bit></bit><move-working-space/><bit><id-bit>1158</id-bit><no-cutting/><sub-bit><id>1159</id><plate>115</plate><slot>9</slot><grip-center><x>-277.89635187651714</x><y>55.542645298252495</y></grip-center><rotation>52.30994292691505</rotation><pos-in-layer><x>104.08152046658779</x><y>1115.5426452982524</y></pos-in-layer><point><id>0</id><x>-76.50001136713313</x><y>9.49992457013937</y></point><point><id>1</id><x>28.499988632866874</x><y>-8.50007542986063</y></point><ref-line-rot>-9.727578551401624</ref-line-rot></sub-bit></bit><move-working-space/><bit><id-bit>1159</id-bit><no-cutting/><sub-bit><id>1160</id><plate>115</plate><slot>10</slot><grip-center><x>-256.95213866960665</x><y>37.19111602797255</y></grip-center><rotation>52.30994292691505</rotation><pos-in-layer><x>125.02573367349828</x><y>1097.1911160279726</y></pos-in-layer><point><id>0</id><x>76.50000970686474</x><y>-9.499915821250056</y></point><point><id>1</id><x>-76.49999029313526</x><y>8.500084178749944</y></point><ref-line-rot>-6.709836807756951</ref-line-rot></sub-bit></bit><move-working-space/><bit><id-bit>1160</id-bit><no-cutting/><sub-bit><id>1161</id><plate>116</plate><slot>1</slot><grip-center><x>-250.22934510059005</x><y>-0.07650104726179036</y></grip-center><rotation>52.30994292691505</rotation><pos-in-layer><x>131.74852724251514</x><y>1059.923498952738</y></pos-in-layer><point><id>0</id><x>-76.49999313082108</x><y>-8.500078900445516</y></point><point><id>1</id><x>76.50000686917892</x><y>9.499921099554484</y></point><ref-line-rot>6.709836807756951</ref-line-rot></sub-bit></bit><move-working-space/><bit><id-bit>1161</id-bit><no-cutting/><sub-bit><id>1162</id><plate>116</plate><slot>2</slot><grip-center><x>-237.34178018268307</x><y>-29.48625187226469</y></grip-center><rotation>52.30994292691505</rotation><pos-in-layer><x>144.63609216042187</x><y>1030.5137481277352</y></pos-in-layer><point><id>0</id><x>-50.510351290384136</x><y>9.499948096709545</y></point><point><id>1</id><x>75.48964870961586</x><y>-8.500051903290455</y></point><ref-line-rot>-8.130102354156005</ref-line-rot></sub-bit></bit><move-working-space/><bit><id-bit>1162</id-bit><no-cutting/><sub-bit><id>1163</id><plate>116</plate><slot>3</slot><grip-center><x>-221.92914967585847</x><y>-55.47593827562755</y></grip-center><rotation>52.30994292691505</rotation><pos-in-layer><x>160.04872266724624</x><y>1004.5240617243725</y></pos-in-layer><point><id>0</id><x>-16.570500909354962</x><y>6.4999848389578005</y></point><point><id>1</id><x>76.42949909064504</x><y>-8.5000151610422</y></point><ref-line-rot>-9.162347045721706</ref-line-rot></sub-bit></bit><move-working-space/><bit><id-bit>1163</id-bit><no-cutting/><sub-bit><id>1164</id><plate>116</plate><slot>4</slot><grip-center><x>-203.826639073968</x><y>-77.37603739749592</y></grip-center><rotation>52.30994292691505</rotation><pos-in-layer><x>178.1512332691368</x><y>982.6239626025041</y></pos-in-layer><point><id>0</id><x>23.074695344503738</x><y>6.500040027881127</y></point><point><id>1</id><x>77.07469534450374</x><y>-8.499959972118873</y></point><ref-line-rot>-15.524110996754272</ref-line-rot></sub-bit></bit><move-working-space/><bit><id-bit>1164</id-bit><no-cutting/><sub-bit><id>1165</id><plate>116</plate><slot>5</slot><grip-center><x>-173.84478627065943</x><y>-79.17060049762533</y></grip-center><rotation>-37.69005707308495</rotation><pos-in-layer><x>208.13308607244562</x><y>980.8293995023747</y></pos-in-layer><point><id>0</id><x>64.28174532550325</x><y>-8.499941369111923</y></point><point><id>1</id><x>77.28174532550325</x><y>9.500058630888077</y></point><ref-line-rot>54.16234704572172</ref-line-rot></sub-bit></bit><move-working-space><go-to><x>2049.120152134989</x></go-to></move-working-space><bit><id-bit>1165</id-bit><no-cutting/><sub-bit><id>1166</id><plate>116</plate><slot>6</slot><grip-center><x>-166.05127798362682</x><y>-50.98537546774293</y></grip-center><rotation>-37.69005707308495</rotation><pos-in-layer><x>84.82856988138428</x><y>1009.0146245322571</y></pos-in-layer><point><id>0</id><x>32.751599675036914</x><y>-8.499969317034868</y></point><point><id>1</id><x>74.75159967503691</x><y>9.500030682965132</y></point><ref-line-rot>23.198590513648202</ref-line-rot></sub-bit></bit><move-working-space><go-to><x>2043.0738015581542</x></go-to></move-working-space><bit><id-bit>1166</id-bit><no-cutting/><sub-bit><id>1167</id><plate>116</plate><slot>7</slot><grip-center><x>-162.41464171861605</x><y>52.40177853778805</y></grip-center><rotation>-37.69005707308495</rotation><pos-in-layer><x>94.51155672322966</x><y>1112.401778537788</y></pos-in-layer><point><id>0</id><x>-21.967008404695846</x><y>6.500002164516921</y></point><point><id>1</id><x>77.03299159530415</x><y>-8.499997835483079</y></point><ref-line-rot>-8.615648184164108</ref-line-rot></sub-bit></bit><move-working-space/><bit><id-bit>1167</id-bit><no-cutting/><sub-bit><id>1168</id><plate>116</plate><slot>8</slot><grip-center><x>-160.7305684737874</x><y>-19.65508430256542</y></grip-center><rotation>-37.69005707308495</rotation><pos-in-layer><x>96.19562996805826</x><y>1040.3449156974345</y></pos-in-layer><point><id>0</id><x>4.7266918923741486</x><y>6.500003512275029</y></point><point><id>1</id><x>76.72669189237415</x><y>-8.499996487724971</y></point><ref-line-rot>-11.76828893202063</ref-line-rot></sub-bit></bit><move-working-space/><bit><id-bit>1168</id-bit><no-cutting/><sub-bit><id>1169</id><plate>116</plate><slot>9</slot><grip-center><x>-158.86978423482964</x><y>14.391243755480208</y></grip-center><rotation>-37.69005707308495</rotation><pos-in-layer><x>98.05641420701613</x><y>1074.3912437554802</y></pos-in-layer><point><id>0</id><x>-13.709239163172342</x><y>6.49999343864873</y></point><point><id>1</id><x>76.29076083682766</x><y>-8.50000656135127</y></point><ref-line-rot>-9.462322208025613</ref-line-rot></sub-bit></bit><move-working-space><go-to><x>2362.053563087467</x></go-to></move-working-space><bit><id-bit>1169</id-bit><no-cutting/><sub-bit><id>1170</id><plate>116</plate><slot>10</slot><grip-center><x>140.99296307907258</x><y>-8.560675918734876</y></grip-center><rotation>-37.69005707308495</rotation><pos-in-layer><x>78.93939999160557</x><y>1051.439324081265</y></pos-in-layer><point><id>0</id><x>-76.50000782813967</x><y>9.499919210175662</y></point><point><id>1</id><x>-28.500007828139672</x><y>-8.500080789824338</y></point><ref-line-rot>-20.55604521958346</ref-line-rot></sub-bit></bit><move-working-space/><bit><id-bit>1170</id-bit><no-cutting/><sub-bit><id>1171</id><plate>117</plate><slot>1</slot><grip-center><x>141.88334872839997</x><y>26.11165304431622</y></grip-center><rotation>-37.69005707308495</rotation><pos-in-layer><x>79.8297856409331</x><y>1086.1116530443162</y></pos-in-layer><point><id>0</id><x>-76.50001310644404</x><y>9.499922669843258</y></point><point><id>1</id><x>-46.500013106444044</x><y>-8.500077330156742</y></point><ref-line-rot>-30.96375653207352</ref-line-rot></sub-bit></bit><move-working-space/><bit><id-bit>1171</id-bit><no-cutting/><sub-bit><id>1172</id><plate>117</plate><slot>2</slot><grip-center><x>146.27156060363257</x><y>57.80620871382457</y></grip-center><rotation>-37.69005707308495</rotation><pos-in-layer><x>84.21799751616572</x><y>1117.8062087138246</y></pos-in-layer><point><id>0</id><x>-76.50001227085122</x><y>-8.500081783785646</y></point><point><id>1</id><x>-71.50001227085122</x><y>9.499918216214354</y></point><ref-line-rot>74.47588900324574</ref-line-rot></sub-bit></bit><move-working-space/><bit><id-bit>1172</id-bit><no-cutting/><sub-bit><id>1173</id><plate>117</plate><slot>3</slot><grip-center><x>146.58192432342412</x><y>-47.272009826997326</y></grip-center><rotation>-37.69005707308495</rotation><pos-in-layer><x>84.52836123595716</x><y>1012.7279901730027</y></pos-in-layer><point><id>0</id><x>-76.5000086637325</x><y>9.499923663804537</y></point><point><id>1</id><x>-22.5000086637325</x><y>-8.500076336195463</y></point><ref-line-rot>-18.434948822922017</ref-line-rot></sub-bit></bit><move-working-space/><bit><id-bit>1173</id-bit><no-cutting/><sub-bit><id>1174</id><plate>117</plate><slot>4</slot><grip-center><x>181.2246536734363</x><y>66.25200709820649</y></grip-center><rotation>52.30994292691505</rotation><pos-in-layer><x>119.17109058596952</x><y>1126.2520070982064</y></pos-in-layer><point><id>0</id><x>-76.50000820251638</x><y>9.499920227274103</y></point><point><id>1</id><x>4.4999917974836166</x><y>-8.500079772725897</y></point><ref-line-rot>-12.52880770915149</ref-line-rot></sub-bit></bit><move-working-space/><bit><id-bit>1174</id-bit><no-cutting/><sub-bit><id>1175</id><plate>117</plate><slot>5</slot><grip-center><x>201.01849039351333</x><y>46.45555552779991</y></grip-center><rotation>52.30994292691505</rotation><pos-in-layer><x>138.96492730604632</x><y>1106.4555555278</y></pos-in-layer><point><id>0</id><x>-76.50001265614529</x><y>9.499919391681175</y></point><point><id>1</id><x>49.49998734385471</x><y>-8.500080608318825</y></point><ref-line-rot>-8.130102354156005</ref-line-rot></sub-bit></bit><move-working-space/><bit><id-bit>1175</id-bit><no-cutting/><sub-bit><id>1176</id><plate>117</plate><slot>6</slot><grip-center><x>215.3443582360676</x><y>19.116574846642482</y></grip-center><rotation>52.30994292691505</rotation><pos-in-layer><x>153.29079514860086</x><y>1079.1165748466424</y></pos-in-layer><point><id>0</id><x>-76.50000919647763</x><y>-8.50007533001434</y></point><point><id>1</id><x>76.49999080352237</x><y>9.49992466998566</y></point><ref-line-rot>6.709836807756951</ref-line-rot></sub-bit></bit><move-working-space/><bit><id-bit>1176</id-bit><no-cutting/><sub-bit><id>1177</id><plate>117</plate><slot>7</slot><grip-center><x>220.42637617439402</x><y>-20.499919188518977</y></grip-center><rotation>52.30994292691505</rotation><pos-in-layer><x>158.37281308692718</x><y>1039.500080811481</y></pos-in-layer><point><id>0</id><x>-76.50001365010651</x><y>-8.500076165607197</y></point><point><id>1</id><x>76.49998634989349</x><y>9.499923834392803</y></point><ref-line-rot>6.709836807756951</ref-line-rot></sub-bit></bit><move-working-space/><bit><id-bit>1177</id-bit><no-cutting/><sub-bit><id>1178</id><plate>117</plate><slot>8</slot><grip-center><x>235.77584980245317</x><y>-46.5520184771144</y></grip-center><rotation>52.30994292691505</rotation><pos-in-layer><x>173.72228671498624</x><y>1013.4479815228856</y></pos-in-layer><point><id>0</id><x>-44.319417101468844</x><y>6.499955175488964</y></point><point><id>1</id><x>75.68058289853116</x><y>-8.500044824511036</y></point><ref-line-rot>-7.1250163489018075</ref-line-rot></sub-bit></bit><move-working-space/><bit><id-bit>1178</id-bit><no-cutting/><sub-bit><id>1179</id><plate>117</plate><slot>9</slot><grip-center><x>254.77855415490438</x><y>-67.48649572538184</y></grip-center><rotation>52.30994292691505</rotation><pos-in-layer><x>192.7249910674377</x><y>992.5135042746182</y></pos-in-layer><point><id>0</id><x>-2.3420412180957015</x><y>6.500014105542448</y></point><point><id>1</id><x>75.6579587819043</x><y>-8.499985894457552</y></point><ref-line-rot>-10.885527054658711</ref-line-rot></sub-bit></bit><move-working-space/><bit><id-bit>1179</id-bit><no-cutting/><sub-bit><id>1180</id><plate>117</plate><slot>10</slot><grip-center><x>273.3669417116945</x><y>-79.70886835920315</y></grip-center><rotation>52.30994292691505</rotation><pos-in-layer><x>211.31337862422743</x><y>980.2911316407968</y></pos-in-layer><point><id>0</id><x>-58.74135777500012</x><y>-9.134823698064167</y></point><point><id>1</id><x>-76.74135777500013</x><y>-2.1348236980641673</y></point><ref-line-rot>-21.250505507133237</ref-line-rot></sub-bit></bit><move-working-space/><bit><id-bit>1180</id-bit><no-cutting/><sub-bit><id>1181</id><plate>118</plate><slot>1</slot><grip-center><x>291.35798989771547</x><y>-60.51988452088641</y></grip-center><rotation>-37.69005707308495</rotation><pos-in-layer><x>229.30442681024851</x><y>999.4801154791136</y></pos-in-layer><point><id>0</id><x>67.22265842499519</x><y>-8.499941604241995</y></point><point><id>1</id><x>77.22265842499519</x><y>9.500058395758005</y></point><ref-line-rot>60.94539590092286</ref-line-rot></sub-bit></bit><move-working-space><go-to><x>2513.9936681416875</x></go-to></move-working-space><bit><id-bit>1181</id-bit><no-cutting/><sub-bit><id>1182</id><plate>118</plate><slot>2</slot><grip-center><x>294.0706694393589</x><y>42.9172758596436</y></grip-center><rotation>-37.69005707308495</rotation><pos-in-layer><x>80.07700129767136</x><y>1102.9172758596435</y></pos-in-layer><point><id>0</id><x>14.05415817481071</x><y>6.500040887202232</y></point><point><id>1</id><x>77.05415817481071</x><y>-8.499959112797768</y></point><ref-line-rot>-13.392497753751098</ref-line-rot></sub-bit></bit><move-working-space/><bit><id-bit>1182</id-bit><no-cutting/><sub-bit><id>1183</id><plate>118</plate><slot>3</slot><grip-center><x>296.3266553813629</x><y>-29.216292426180374</y></grip-center><rotation>-37.69005707308495</rotation><pos-in-layer><x>82.33298723967528</x><y>1030.7837075738196</y></pos-in-layer><point><id>0</id><x>39.51451086379967</x><y>6.500039833155341</y></point><point><id>1</id><x>75.51451086379967</x><y>-8.499960166844659</y></point><ref-line-rot>-22.61986494804042</ref-line-rot></sub-bit></bit><move-working-space/><bit><id-bit>1183</id-bit><no-cutting/><sub-bit><id>1184</id><plate>118</plate><slot>4</slot><grip-center><x>297.96756460681485</x><y>4.919029115398033</y></grip-center><rotation>-37.69005707308495</rotation><pos-in-layer><x>83.97389646512738</x><y>1064.9190291153982</y></pos-in-layer><point><id>0</id><x>21.46163126984635</x><y>6.500028727119684</y></point><point><id>1</id><x>75.46163126984635</x><y>-8.499971272880316</y></point><ref-line-rot>-15.524110996754272</ref-line-rot></sub-bit></bit></layer><layer><layer-height>363.0</layer-height><move-working-space><go-to><x>1918.623440875609</x></go-to></move-working-space><bit><id-bit>1184</id-bit><no-cutting/><sub-bit><id>1185</id><plate>118</plate><slot>5</slot><grip-center><x>-314.04324766651666</x><y>19.14437549570802</y></grip-center><rotation>-37.52010385357049</rotation><pos-in-layer><x>67.33331145787429</x><y>1079.1443754957081</y></pos-in-layer><point><id>0</id><x>-76.50002173583789</x><y>6.499859139762407</y></point><point><id>1</id><x>-69.50002173583789</x><y>-8.500140860237593</y></point><ref-line-rot>-64.98310652189998</ref-line-rot></sub-bit></bit><move-working-space/><bit><id-bit>1185</id-bit><no-cutting/><sub-bit><id>1186</id><plate>118</plate><slot>6</slot><grip-center><x>-312.2119191941828</x><y>-17.09113457233428</y></grip-center><rotation>-37.52010385357049</rotation><pos-in-layer><x>69.16463993020807</x><y>1042.9088654276657</y></pos-in-layer><point><id>0</id><x>-76.50002228154008</x><y>6.499860014152006</y></point><point><id>1</id><x>-58.50002228154008</x><y>-8.500139985847994</y></point><ref-line-rot>-39.80557109226519</ref-line-rot></sub-bit></bit><move-working-space/><bit><id-bit>1186</id-bit><no-cutting/><sub-bit><id>1187</id><plate>118</plate><slot>7</slot><grip-center><x>-286.13758234887234</x><y>60.60349204244722</y></grip-center><rotation>52.4798961464295</rotation><pos-in-layer><x>95.2389767755185</x><y>1120.6034920424472</y></pos-in-layer><point><id>0</id><x>-76.50001306117029</x><y>0.49985353547208433</y></point><point><id>1</id><x>-4.500013061170293</x><y>-8.500146464527916</y></point><ref-line-rot>-7.125016348901757</ref-line-rot></sub-bit></bit><move-working-space/><bit><id-bit>1187</id-bit><no-cutting/><sub-bit><id>1188</id><plate>118</plate><slot>8</slot><grip-center><x>-265.10838816948035</x><y>46.76011010157127</y></grip-center><rotation>52.4798961464295</rotation><pos-in-layer><x>116.2681709549106</x><y>1106.7601101015712</y></pos-in-layer><point><id>0</id><x>-76.50001972690814</x><y>9.499859080167568</y></point><point><id>1</id><x>55.499980273091865</x><y>-8.500140919832432</y></point><ref-line-rot>-7.765166018425354</ref-line-rot></sub-bit></bit><move-working-space/><bit><id-bit>1188</id-bit><no-cutting/><sub-bit><id>1189</id><plate>118</plate><slot>9</slot><grip-center><x>-251.69378210865406</x><y>18.36150306864706</y></grip-center><rotation>52.4798961464295</rotation><pos-in-layer><x>129.68277701573697</x><y>1078.361503068647</y></pos-in-layer><point><id>0</id><x>-76.50002060129793</x><y>-8.500141465534597</y></point><point><id>1</id><x>76.49997939870207</x><y>9.499858534465403</y></point><ref-line-rot>6.709836807756951</ref-line-rot></sub-bit></bit><move-working-space/><bit><id-bit>1189</id-bit><no-cutting/><sub-bit><id>1190</id><plate>118</plate><slot>10</slot><grip-center><x>-242.49895142697858</x><y>-16.068252186680354</y></grip-center><rotation>52.4798961464295</rotation><pos-in-layer><x>138.87760769741226</x><y>1043.9317478133196</y></pos-in-layer><point><id>0</id><x>-63.89014818792779</x><y>-8.500119154826335</y></point><point><id>1</id><x>77.10985181207221</x><y>9.499880845173665</y></point><ref-line-rot>7.275004957889231</ref-line-rot></sub-bit></bit><move-working-space/><bit><id-bit>1190</id-bit><no-cutting/><sub-bit><id>1191</id><plate>119</plate><slot>1</slot><grip-center><x>-228.13798616926798</x><y>-43.563316407079405</y></grip-center><rotation>52.4798961464295</rotation><pos-in-layer><x>153.2385729551229</x><y>1016.4366835929206</y></pos-in-layer><point><id>0</id><x>-35.31677199295035</x><y>6.499942161355108</y></point><point><id>1</id><x>75.68322800704965</x><y>-8.500057838644892</y></point><ref-line-rot>-7.6960517220165565</ref-line-rot></sub-bit></bit><move-working-space/><bit><id-bit>1191</id-bit><no-cutting/><sub-bit><id>1192</id><plate>119</plate><slot>2</slot><grip-center><x>-211.2928772986215</x><y>-67.56462604737784</y></grip-center><rotation>52.4798961464295</rotation><pos-in-layer><x>170.08368182576942</x><y>992.4353739526222</y></pos-in-layer><point><id>0</id><x>3.107561174636146</x><y>6.500019620748915</y></point><point><id>1</id><x>75.10756117463615</x><y>-8.499980379251085</y></point><ref-line-rot>-11.76828893202063</ref-line-rot></sub-bit></bit><move-working-space/><bit><id-bit>1192</id-bit><no-cutting/><sub-bit><id>1193</id><plate>119</plate><slot>3</slot><grip-center><x>-192.49638310014342</x><y>-86.30085167928199</y></grip-center><rotation>52.4798961464295</rotation><pos-in-layer><x>188.8801760242477</x><y>973.699148320718</y></pos-in-layer><point><id>0</id><x>51.45464728665911</x><y>6.500130625463569</y></point><point><id>1</id><x>75.45464728665911</x><y>-8.49986937453643</y></point><ref-line-rot>-32.005383208083494</ref-line-rot></sub-bit></bit><move-working-space/><bit><id-bit>1193</id-bit><no-cutting/><sub-bit><id>1194</id><plate>119</plate><slot>4</slot><grip-center><x>-168.33451164122033</x><y>-66.2995517105413</y></grip-center><rotation>-37.52010385357049</rotation><pos-in-layer><x>213.0420474831708</x><y>993.7004482894587</y></pos-in-layer><point><id>0</id><x>47.708568744301466</x><y>-8.499916633883087</y></point><point><id>1</id><x>74.70856874430146</x><y>9.500083366116913</y></point><ref-line-rot>33.6900675259798</ref-line-rot></sub-bit></bit><move-working-space><go-to><x>2033.4361633142403</x></go-to></move-working-space><bit><id-bit>1194</id-bit><no-cutting/><sub-bit><id>1195</id><plate>119</plate><slot>5</slot><grip-center><x>-163.38843341868434</x><y>67.61964392220725</y></grip-center><rotation>-37.52010385357049</rotation><pos-in-layer><x>103.17540326707558</x><y>1127.6196439222072</y></pos-in-layer><point><id>0</id><x>20.382996286397457</x><y>-6.556287511829922</y></point><point><id>1</id><x>-75.61700371360254</x><y>-6.556287511829922</y></point><ref-line-rot>-0.0</ref-line-rot></sub-bit></bit><move-working-space/><bit><id-bit>1195</id-bit><no-cutting/><sub-bit><id>1196</id><plate>119</plate><slot>6</slot><grip-center><x>-161.49952970075378</x><y>-36.410567324118354</y></grip-center><rotation>-37.52010385357049</rotation><pos-in-layer><x>105.06430698500617</x><y>1023.5894326758817</y></pos-in-layer><point><id>0</id><x>18.659516083078017</x><y>9.500032559315628</y></point><point><id>1</id><x>75.65951608307802</x><y>-8.499967440684372</y></point><ref-line-rot>-17.525568373722855</ref-line-rot></sub-bit></bit><move-working-space/><bit><id-bit>1196</id-bit><no-cutting/><sub-bit><id>1197</id><plate>119</plate><slot>7</slot><grip-center><x>-157.68931753907154</x><y>31.434754565825468</y></grip-center><rotation>-37.52010385357049</rotation><pos-in-layer><x>108.87451914668827</x><y>1091.4347545658254</y></pos-in-layer><point><id>0</id><x>-22.363359511585315</x><y>6.499982638911071</y></point><point><id>1</id><x>76.63664048841468</x><y>-8.50001736108893</y></point><ref-line-rot>-8.615648184164108</ref-line-rot></sub-bit></bit><move-working-space/><bit><id-bit>1197</id-bit><no-cutting/><sub-bit><id>1198</id><plate>119</plate><slot>8</slot><grip-center><x>-157.534245589462</x><y>-4.047704098790241</y></grip-center><rotation>-37.52010385357049</rotation><pos-in-layer><x>109.02959109629774</x><y>1055.9522959012097</y></pos-in-layer><point><id>0</id><x>-7.5022657855022885</x><y>6.499995634000854</y></point><point><id>1</id><x>76.49773421449771</x><y>-8.500004365999146</y></point><ref-line-rot>-10.124671655397842</ref-line-rot></sub-bit></bit><move-working-space><go-to><x>2363.0620333623165</x></go-to></move-working-space><bit><id-bit>1198</id-bit><no-cutting/><sub-bit><id>1199</id><plate>119</plate><slot>9</slot><grip-center><x>140.5832609217243</x><y>10.44802894860019</y></grip-center><rotation>-37.52010385357049</rotation><pos-in-layer><x>77.52122755940763</x><y>1070.4480289486</y></pos-in-layer><point><id>0</id><x>-76.50002371896724</x><y>9.499858251218484</y></point><point><id>1</id><x>-31.500023718967242</x><y>-8.500141748781516</y></point><ref-line-rot>-21.80140948635181</ref-line-rot></sub-bit></bit><move-working-space><go-to><x>2356.3644779096007</x></go-to></move-working-space><bit><id-bit>1199</id-bit><no-cutting/><sub-bit><id>1200</id><plate>119</plate><slot>10</slot><grip-center><x>141.74688411041498</x><y>-25.59644116046001</y></grip-center><rotation>-37.52010385357049</rotation><pos-in-layer><x>85.38240620081433</x><y>1034.40355883954</y></pos-in-layer><point><id>0</id><x>-76.50002426466939</x><y>9.49985912560821</y></point><point><id>1</id><x>-16.500024264669392</x><y>-8.50014087439179</y></point><ref-line-rot>-16.699244233993618</ref-line-rot></sub-bit></bit><move-working-space/><bit><id-bit>1200</id-bit><no-cutting/><sub-bit><id>1201</id><plate>120</plate><slot>1</slot><grip-center><x>143.84540466709916</x><y>43.26346428270755</y></grip-center><rotation>-37.52010385357049</rotation><pos-in-layer><x>87.48092675749831</x><y>1103.2634642827074</y></pos-in-layer><point><id>0</id><x>-76.5000231732651</x><y>9.499857376828743</y></point><point><id>1</id><x>-54.500023173265106</x><y>-8.500142623171257</y></point><ref-line-rot>-39.28940686250036</ref-line-rot></sub-bit></bit><move-working-space/><bit><id-bit>1201</id-bit><no-cutting/><sub-bit><id>1202</id><plate>120</plate><slot>2</slot><grip-center><x>151.98222981486776</x><y>-63.19305910654491</y></grip-center><rotation>-37.52010385357049</rotation><pos-in-layer><x>95.61775190526714</x><y>996.8069408934551</y></pos-in-layer><point><id>0</id><x>-76.50000142300408</x><y>0.49985206860100817</y></point><point><id>1</id><x>-25.50000142300408</x><y>-8.500147931398992</y></point><ref-line-rot>-10.00797980144135</ref-line-rot></sub-bit></bit><move-working-space/><bit><id-bit>1202</id-bit><no-cutting/><sub-bit><id>1203</id><plate>120</plate><slot>3</slot><grip-center><x>171.4662296273107</x><y>73.63684929872909</y></grip-center><rotation>52.4798961464295</rotation><pos-in-layer><x>115.10175171771016</x><y>1133.636849298729</y></pos-in-layer><point><id>0</id><x>-76.50002502098181</x><y>9.499852098044911</y></point><point><id>1</id><x>-25.50002502098181</x><y>-8.500147901955089</y></point><ref-line-rot>-19.44003482817619</ref-line-rot></sub-bit></bit><move-working-space/><bit><id-bit>1203</id-bit><no-cutting/><sub-bit><id>1204</id><plate>120</plate><slot>4</slot><grip-center><x>192.6953972557658</x><y>57.20351951524775</y></grip-center><rotation>52.4798961464295</rotation><pos-in-layer><x>136.33091934616505</x><y>1117.2035195152478</y></pos-in-layer><point><id>0</id><x>-76.50001796397459</x><y>9.499857642740409</y></point><point><id>1</id><x>28.499982036025415</x><y>-8.500142357259591</y></point><ref-line-rot>-9.727578551401624</ref-line-rot></sub-bit></bit><move-working-space/><bit><id-bit>1204</id-bit><no-cutting/><sub-bit><id>1205</id><plate>120</plate><slot>5</slot><grip-center><x>210.53617784052423</x><y>34.42336897944163</y></grip-center><rotation>52.4798961464295</rotation><pos-in-layer><x>154.1716999309233</x><y>1094.4233689794416</y></pos-in-layer><point><id>0</id><x>-76.50001883836427</x><y>9.499857097038301</y></point><point><id>1</id><x>67.49998116163573</x><y>-8.500142902961699</y></point><ref-line-rot>-7.125016348901757</ref-line-rot></sub-bit></bit><move-working-space/><bit><id-bit>1205</id-bit><no-cutting/><sub-bit><id>1206</id><plate>120</plate><slot>6</slot><grip-center><x>219.300500005403</x><y>-0.3660274344180489</y></grip-center><rotation>52.4798961464295</rotation><pos-in-layer><x>162.93602209580195</x><y>1059.633972565582</y></pos-in-layer><point><id>0</id><x>-76.50001971275404</x><y>-8.500143448663806</y></point><point><id>1</id><x>76.49998028724596</x><y>9.499856551336194</y></point><ref-line-rot>6.709836807756951</ref-line-rot></sub-bit></bit><move-working-space/><bit><id-bit>1206</id-bit><no-cutting/><sub-bit><id>1207</id><plate>120</plate><slot>7</slot><grip-center><x>228.46152667329815</x><y>-34.64035567748347</y></grip-center><rotation>52.4798961464295</rotation><pos-in-layer><x>172.09704876369733</x><y>1025.3596443225165</y></pos-in-layer><point><id>0</id><x>-66.21586525879009</x><y>6.499887776285476</y></point><point><id>1</id><x>74.78413474120991</x><y>-8.500112223714524</y></point><ref-line-rot>-6.072456407207751</ref-line-rot></sub-bit></bit><move-working-space/><bit><id-bit>1207</id-bit><no-cutting/><sub-bit><id>1208</id><plate>120</plate><slot>8</slot><grip-center><x>246.21149745032614</x><y>-57.5479447187395</y></grip-center><rotation>52.4798961464295</rotation><pos-in-layer><x>189.84701954072534</x><y>1002.4520552812605</y></pos-in-layer><point><id>0</id><x>-26.070072784160388</x><y>6.499972514736697</y></point><point><id>1</id><x>75.92992721583961</x><y>-8.500027485263303</y></point><ref-line-rot>-8.36588612403259</ref-line-rot></sub-bit></bit><move-working-space/><bit><id-bit>1208</id-bit><no-cutting/><sub-bit><id>1209</id><plate>120</plate><slot>9</slot><grip-center><x>267.27310276613235</x><y>-74.25643105129299</y></grip-center><rotation>52.4798961464295</rotation><pos-in-layer><x>210.90862485653133</x><y>985.743568948707</y></pos-in-layer><point><id>0</id><x>29.284360086145398</x><y>6.500104260480555</y></point><point><id>1</id><x>77.2843600861454</x><y>-8.499895739519445</y></point><ref-line-rot>-17.354024636261332</ref-line-rot></sub-bit></bit><move-working-space><go-to><x>2507.874733373746</x></go-to></move-working-space><bit><id-bit>1209</id-bit><no-cutting/><sub-bit><id>1210</id><plate>120</plate><slot>10</slot><grip-center><x>287.2845954833138</x><y>62.701216907541834</y></grip-center><rotation>-37.52010385357049</rotation><pos-in-layer><x>79.40986210956771</x><y>1122.701216907542</y></pos-in-layer><point><id>0</id><x>-23.39625588379377</x><y>-7.583925317046351</y></point><point><id>1</id><x>-77.39625588379377</x><y>1.4160746829536492</y></point><ref-line-rot>-9.46232220802565</ref-line-rot></sub-bit></bit><move-working-space/><bit><id-bit>1210</id-bit><no-cutting/><sub-bit><id>1211</id><plate>121</plate><slot>1</slot><grip-center><x>294.85586209627</x><y>-44.09039503964356</y></grip-center><rotation>-37.52010385357049</rotation><pos-in-layer><x>86.98112872252386</x><y>1015.9096049603564</y></pos-in-layer><point><id>0</id><x>55.00381810564966</x><y>9.50009931088698</y></point><point><id>1</id><x>76.00381810564966</x><y>-8.49990068911302</y></point><ref-line-rot>-40.60129464500447</ref-line-rot></sub-bit></bit><move-working-space/><bit><id-bit>1211</id-bit><no-cutting/><sub-bit><id>1212</id><plate>121</plate><slot>2</slot><grip-center><x>296.8813644931671</x><y>24.872779628306873</y></grip-center><rotation>-37.52010385357049</rotation><pos-in-layer><x>89.00663111942094</x><y>1084.872779628307</y></pos-in-layer><point><id>0</id><x>17.766505186819792</x><y>6.500059880602464</y></point><point><id>1</id><x>74.76650518681978</x><y>-8.499940119397536</y></point><ref-line-rot>-14.743562836470744</ref-line-rot></sub-bit></bit><move-working-space/><bit><id-bit>1212</id-bit><no-cutting/><sub-bit><id>1213</id><plate>121</plate><slot>3</slot><grip-center><x>297.99754539859396</x><y>-11.177031399996103</y></grip-center><rotation>-37.52010385357049</rotation><pos-in-layer><x>90.12281202484792</x><y>1048.822968600004</y></pos-in-layer><point><id>0</id><x>32.9923002128682</x><y>6.500067452358508</y></point><point><id>1</id><x>74.9923002128682</x><y>-8.499932547641492</y></point><ref-line-rot>-19.653824058053313</ref-line-rot></sub-bit></bit></layer><layer><layer-height>371.25</layer-height><move-working-space><go-to><x>1919.6986914492888</x></go-to></move-working-space><bit><id-bit>1213</id-bit><no-cutting/><sub-bit><id>1214</id><plate>121</plate><slot>4</slot><grip-center><x>-312.6214865203373</x><y>-0.09244792370344612</y></grip-center><rotation>-37.350044244452896</rotation><pos-in-layer><x>67.67982203037377</x><y>1059.9075520762965</y></pos-in-layer><point><id>0</id><x>-76.50001144400878</x><y>9.499936986512267</y></point><point><id>1</id><x>-61.50001144400878</x><y>-8.500063013487733</y></point><ref-line-rot>-50.1944289077348</ref-line-rot></sub-bit></bit><move-working-space/><bit><id-bit>1214</id-bit><no-cutting/><sub-bit><id>1215</id><plate>121</plate><slot>5</slot><grip-center><x>-306.77361332324324</x><y>-35.849584323872605</y></grip-center><rotation>-37.350044244452896</rotation><pos-in-layer><x>73.5276952274678</x><y>1024.1504156761275</y></pos-in-layer><point><id>0</id><x>-76.5000032916088</x><y>1.499938874328194</y></point><point><id>1</id><x>-58.500003291608806</x><y>-8.500061125671806</y></point><ref-line-rot>-29.05460409907715</ref-line-rot></sub-bit></bit><move-working-space/><bit><id-bit>1215</id-bit><no-cutting/><sub-bit><id>1216</id><plate>121</plate><slot>6</slot><grip-center><x>-274.49288440587736</x><y>54.52828651122756</y></grip-center><rotation>52.65030335821649</rotation><pos-in-layer><x>105.80842414483391</x><y>1114.5282865112276</y></pos-in-layer><point><id>0</id><x>-76.50006068319965</x><y>9.499802922394169</y></point><point><id>1</id><x>31.49993931680035</x><y>-8.500197077605831</y></point><ref-line-rot>-9.46232220802565</ref-line-rot></sub-bit></bit><move-working-space/><bit><id-bit>1216</id-bit><no-cutting/><sub-bit><id>1217</id><plate>121</plate><slot>7</slot><grip-center><x>-253.84642070004787</x><y>35.746349866529386</y></grip-center><rotation>52.65030335821649</rotation><pos-in-layer><x>126.45488785066323</x><y>1095.7463498665293</y></pos-in-layer><point><id>0</id><x>76.5000625709944</x><y>-9.499582049689906</y></point><point><id>1</id><x>-76.4999374290056</x><y>8.500417950310094</y></point><ref-line-rot>-6.709836807756951</ref-line-rot></sub-bit></bit><move-working-space/><bit><id-bit>1217</id-bit><no-cutting/><sub-bit><id>1218</id><plate>121</plate><slot>8</slot><grip-center><x>-247.1646994703824</x><y>-1.9157025841640691</y></grip-center><rotation>52.6499557555471</rotation><pos-in-layer><x>133.13660908032875</x><y>1058.0842974158359</y></pos-in-layer><point><id>0</id><x>-76.49999024590579</x><y>-8.500060628996295</y></point><point><id>1</id><x>76.50000975409421</x><y>9.499939371003705</y></point><ref-line-rot>6.709836807756951</ref-line-rot></sub-bit></bit><move-working-space/><bit><id-bit>1218</id-bit><no-cutting/><sub-bit><id>1219</id><plate>121</plate><slot>9</slot><grip-center><x>-233.87817704262162</x><y>-30.912521542307683</y></grip-center><rotation>52.6499557555471</rotation><pos-in-layer><x>146.42313150808945</x><y>1029.0874784576922</y></pos-in-layer><point><id>0</id><x>-49.13962503715473</x><y>9.499959621763482</y></point><point><id>1</id><x>76.86037496284527</x><y>-8.500040378236518</y></point><ref-line-rot>-8.130102354156005</ref-line-rot></sub-bit></bit><move-working-space/><bit><id-bit>1219</id-bit><no-cutting/><sub-bit><id>1220</id><plate>121</plate><slot>10</slot><grip-center><x>-218.19254089172838</x><y>-56.64758671234455</y></grip-center><rotation>52.64950028678894</rotation><pos-in-layer><x>162.10876765898252</x><y>1003.3524132876555</y></pos-in-layer><point><id>0</id><x>-14.963396737436131</x><y>6.499889268988866</y></point><point><id>1</id><x>75.03660326256387</x><y>-8.500110731011134</y></point><ref-line-rot>-9.462322208025613</ref-line-rot></sub-bit></bit><move-working-space/><bit><id-bit>1220</id-bit><no-cutting/><sub-bit><id>1221</id><plate>122</plate><slot>1</slot><grip-center><x>-199.84391927446012</x><y>-78.22994539217812</y></grip-center><rotation>52.6499557555471</rotation><pos-in-layer><x>180.4573892762512</x><y>981.7700546078219</y></pos-in-layer><point><id>0</id><x>25.37145417725415</x><y>6.5000270825246815</y></point><point><id>1</id><x>76.37145417725415</x><y>-8.499972917475318</y></point><ref-line-rot>-16.389540334034763</ref-line-rot></sub-bit></bit><move-working-space/><bit><id-bit>1221</id-bit><no-cutting/><sub-bit><id>1222</id><plate>122</plate><slot>2</slot><grip-center><x>-170.82588268350904</x><y>-80.32942151809206</y></grip-center><rotation>-37.350044244452896</rotation><pos-in-layer><x>209.47542586720215</x><y>979.6705784819079</y></pos-in-layer><point><id>0</id><x>64.98708950260405</x><y>-8.499955908269897</y></point><point><id>1</id><x>76.98708950260405</x><y>9.500044091730103</y></point><ref-line-rot>56.30993247402022</ref-line-rot></sub-bit></bit><move-working-space><go-to><x>2049.9820883875973</x></go-to></move-working-space><bit><id-bit>1222</id-bit><no-cutting/><sub-bit><id>1223</id><plate>122</plate><slot>3</slot><grip-center><x>-162.8577562580506</x><y>-52.57647341860579</y></grip-center><rotation>-37.350044244452896</rotation><pos-in-layer><x>87.16015535435236</x><y>1007.4235265813942</y></pos-in-layer><point><id>0</id><x>32.215688654330734</x><y>-8.49997703570824</y></point><point><id>1</id><x>77.21568865433073</x><y>9.50002296429176</y></point><ref-line-rot>21.80140948635181</ref-line-rot></sub-bit></bit><move-working-space><go-to><x>2046.36396876202</x></go-to></move-working-space><bit><id-bit>1223</id-bit><no-cutting/><sub-bit><id>1224</id><plate>122</plate><slot>4</slot><grip-center><x>-157.76135384892783</x><y>49.289039581951116</y></grip-center><rotation>-37.350044244452896</rotation><pos-in-layer><x>95.8746773890523</x><y>1109.289039581951</y></pos-in-layer><point><id>0</id><x>-26.561317372657996</x><y>6.499995054767524</y></point><point><id>1</id><x>75.438682627342</x><y>-8.500004945232476</y></point><ref-line-rot>-8.36588612403259</ref-line-rot></sub-bit></bit></layer></batch></mesh>